{
    "activations": {
        "heap_overlay_pool": {
            "buffer_c_name": "NULL",
            "buffer_c_name_addr": "NULL",
            "buffer_data_size": 0,
            "buffer_offsets": [
                {
                    "buffer_name": "input_0_output_array",
                    "lite_tag": null,
                    "offset": 204,
                    "size": 52,
                    "start_offset": 204
                },
                {
                    "buffer_name": "dense_dense_output_array",
                    "lite_tag": null,
                    "offset": 256,
                    "size": 256,
                    "start_offset": 256
                },
                {
                    "buffer_name": "dense_output_array",
                    "lite_tag": null,
                    "offset": 256,
                    "size": 256,
                    "start_offset": 256
                },
                {
                    "buffer_name": "dense_1_dense_output_array",
                    "lite_tag": null,
                    "offset": 0,
                    "size": 256,
                    "start_offset": 0
                },
                {
                    "buffer_name": "dense_1_output_array",
                    "lite_tag": null,
                    "offset": 256,
                    "size": 256,
                    "start_offset": 256
                },
                {
                    "buffer_name": "dense_2_dense_output_array",
                    "lite_tag": null,
                    "offset": 0,
                    "size": 4,
                    "start_offset": 0
                }
            ],
            "pool_id": 0,
            "pool_size": 512
        }
    },
    "activations_alignment": 4,
    "c_activations_count": 1,
    "c_arrays": [
        {
            "c_bits": 32,
            "c_id": 0,
            "c_mem_pool": "**default**",
            "c_size_in_byte": 52,
            "c_type": "float",
            "format": "float",
            "io_type": "input",
            "is_const": false,
            "mem_pool": "activations",
            "n_items": 13,
            "name": "input_0_output_array",
            "offset": 204,
            "padded": true,
            "raw_fmt": "(FLOAT, 32 bit, C Size: 32 bits)",
            "size": 13,
            "tensors": [
                {
                    "name": "input_0_output",
                    "shape": [
                        1,
                        1,
                        1,
                        13
                    ]
                }
            ]
        },
        {
            "c_bits": 32,
            "c_id": 1,
            "c_mem_pool": "**default**",
            "c_size_in_byte": 256,
            "c_type": "float",
            "format": "float",
            "is_const": false,
            "mem_pool": "activations",
            "n_items": 64,
            "name": "dense_dense_output_array",
            "offset": 256,
            "padded": true,
            "raw_fmt": "(FLOAT, 32 bit, C Size: 32 bits)",
            "size": 64,
            "tensors": [
                {
                    "name": "dense_dense_output",
                    "shape": [
                        1,
                        1,
                        1,
                        64
                    ]
                }
            ]
        },
        {
            "c_bits": 32,
            "c_id": 2,
            "c_mem_pool": "**default**",
            "c_size_in_byte": 256,
            "c_type": "float",
            "format": "float",
            "is_const": false,
            "mem_pool": "activations",
            "n_items": 64,
            "name": "dense_output_array",
            "offset": 256,
            "padded": true,
            "raw_fmt": "(FLOAT, 32 bit, C Size: 32 bits)",
            "size": 64,
            "tensors": [
                {
                    "name": "dense_output",
                    "shape": [
                        1,
                        1,
                        1,
                        64
                    ]
                }
            ]
        },
        {
            "c_bits": 32,
            "c_id": 3,
            "c_mem_pool": "**default**",
            "c_size_in_byte": 256,
            "c_type": "float",
            "format": "float",
            "is_const": false,
            "mem_pool": "activations",
            "n_items": 64,
            "name": "dense_1_dense_output_array",
            "offset": 0,
            "padded": true,
            "raw_fmt": "(FLOAT, 32 bit, C Size: 32 bits)",
            "size": 64,
            "tensors": [
                {
                    "name": "dense_1_dense_output",
                    "shape": [
                        1,
                        1,
                        1,
                        64
                    ]
                }
            ]
        },
        {
            "c_bits": 32,
            "c_id": 4,
            "c_mem_pool": "**default**",
            "c_size_in_byte": 256,
            "c_type": "float",
            "format": "float",
            "is_const": false,
            "mem_pool": "activations",
            "n_items": 64,
            "name": "dense_1_output_array",
            "offset": 256,
            "padded": true,
            "raw_fmt": "(FLOAT, 32 bit, C Size: 32 bits)",
            "size": 64,
            "tensors": [
                {
                    "name": "dense_1_output",
                    "shape": [
                        1,
                        1,
                        1,
                        64
                    ]
                }
            ]
        },
        {
            "c_bits": 32,
            "c_id": 5,
            "c_mem_pool": "**default**",
            "c_size_in_byte": 4,
            "c_type": "float",
            "format": "float",
            "io_type": "output",
            "is_const": false,
            "mem_pool": "activations",
            "n_items": 1,
            "name": "dense_2_dense_output_array",
            "offset": 0,
            "padded": true,
            "raw_fmt": "(FLOAT, 32 bit, C Size: 32 bits)",
            "size": 1,
            "tensors": [
                {
                    "name": "dense_2_dense_output",
                    "shape": [
                        1,
                        1,
                        1,
                        1
                    ]
                }
            ]
        },
        {
            "c_bits": 32,
            "c_id": 6,
            "c_mem_pool": "weights",
            "c_size_in_byte": 3328,
            "c_type": "const float",
            "format": "float",
            "is_const": true,
            "mem_pool": "weights",
            "n_items": 832,
            "name": "dense_dense_weights_array",
            "offset": 0,
            "padded": true,
            "raw_fmt": "(FLOAT, 32 bit, C Size: 32 bits)",
            "size": 832,
            "tensors": [
                {
                    "name": "dense_dense_weights",
                    "shape": [
                        13,
                        1,
                        1,
                        64
                    ]
                }
            ],
            "zeros": 0
        },
        {
            "c_bits": 32,
            "c_id": 7,
            "c_mem_pool": "weights",
            "c_size_in_byte": 256,
            "c_type": "const float",
            "format": "float",
            "is_const": true,
            "mem_pool": "weights",
            "n_items": 64,
            "name": "dense_dense_bias_array",
            "offset": 3328,
            "padded": true,
            "raw_fmt": "(FLOAT, 32 bit, C Size: 32 bits)",
            "size": 64,
            "tensors": [
                {
                    "name": "dense_dense_bias",
                    "shape": [
                        1,
                        1,
                        1,
                        64
                    ]
                }
            ],
            "zeros": 13
        },
        {
            "c_bits": 32,
            "c_id": 8,
            "c_mem_pool": "weights",
            "c_size_in_byte": 16384,
            "c_type": "const float",
            "format": "float",
            "is_const": true,
            "mem_pool": "weights",
            "n_items": 4096,
            "name": "dense_1_dense_weights_array",
            "offset": 3584,
            "padded": true,
            "raw_fmt": "(FLOAT, 32 bit, C Size: 32 bits)",
            "size": 4096,
            "tensors": [
                {
                    "name": "dense_1_dense_weights",
                    "shape": [
                        64,
                        1,
                        1,
                        64
                    ]
                }
            ],
            "zeros": 0
        },
        {
            "c_bits": 32,
            "c_id": 9,
            "c_mem_pool": "weights",
            "c_size_in_byte": 256,
            "c_type": "const float",
            "format": "float",
            "is_const": true,
            "mem_pool": "weights",
            "n_items": 64,
            "name": "dense_1_dense_bias_array",
            "offset": 19968,
            "padded": true,
            "raw_fmt": "(FLOAT, 32 bit, C Size: 32 bits)",
            "size": 64,
            "tensors": [
                {
                    "name": "dense_1_dense_bias",
                    "shape": [
                        1,
                        1,
                        1,
                        64
                    ]
                }
            ],
            "zeros": 12
        },
        {
            "c_bits": 32,
            "c_id": 10,
            "c_mem_pool": "weights",
            "c_size_in_byte": 256,
            "c_type": "const float",
            "format": "float",
            "is_const": true,
            "mem_pool": "weights",
            "n_items": 64,
            "name": "dense_2_dense_weights_array",
            "offset": 20224,
            "padded": true,
            "raw_fmt": "(FLOAT, 32 bit, C Size: 32 bits)",
            "size": 64,
            "tensors": [
                {
                    "name": "dense_2_dense_weights",
                    "shape": [
                        64,
                        1,
                        1,
                        1
                    ]
                }
            ],
            "zeros": 0
        },
        {
            "c_bits": 32,
            "c_id": 11,
            "c_mem_pool": "weights",
            "c_size_in_byte": 4,
            "c_type": "const float",
            "format": "float",
            "is_const": true,
            "mem_pool": "weights",
            "n_items": 1,
            "name": "dense_2_dense_bias_array",
            "offset": 20480,
            "padded": true,
            "raw_fmt": "(FLOAT, 32 bit, C Size: 32 bits)",
            "size": 1,
            "tensors": [
                {
                    "name": "dense_2_dense_bias",
                    "shape": [
                        1,
                        1,
                        1,
                        1
                    ]
                }
            ],
            "zeros": 0
        }
    ],
    "c_arrays_n": 12,
    "c_intq_n": 0,
    "c_layers": [
        {
            "c_forward": "forward_dense",
            "c_id": 0,
            "exec_time": {
                "cycles": 0,
                "cycles_by_macc": 0.0,
                "duration_ms": 0.0011250000534346327,
                "percentage": 20.45454572513891
            },
            "layer_type": "dense",
            "m_id": 0,
            "macc": 896,
            "name": "dense_dense",
            "next": "dense",
            "op_by_type": {
                "smul_f32_f32": 896
            },
            "rom": 3584,
            "tensors": {
                "inputs": [
                    "input_0_output"
                ],
                "outputs": [
                    "dense_dense_output"
                ],
                "scratchs": [],
                "weights": [
                    "dense_dense_weights",
                    "dense_dense_bias"
                ]
            },
            "weight_sparsity": [
                0.014508928571428603,
                896,
                13
            ]
        },
        {
            "c_forward": "forward_relu",
            "c_id": 1,
            "exec_time": {
                "cycles": 0,
                "cycles_by_macc": 0.0,
                "duration_ms": 0.0007500000356230885,
                "percentage": 13.636363816759273
            },
            "layer_type": "nl",
            "m_id": 0,
            "macc": 64,
            "name": "dense",
            "next": "dense_1_dense",
            "op_by_type": {
                "op_f32_f32": 64
            },
            "rom": 0,
            "tensors": {
                "inputs": [
                    "dense_dense_output"
                ],
                "outputs": [
                    "dense_output"
                ],
                "scratchs": [],
                "weights": []
            },
            "weight_sparsity": [
                0.0,
                0,
                0
            ]
        },
        {
            "c_forward": "forward_dense",
            "c_id": 2,
            "exec_time": {
                "cycles": 0,
                "cycles_by_macc": 0.0,
                "duration_ms": 0.0026250000519212335,
                "percentage": 47.727272035756116
            },
            "layer_type": "dense",
            "m_id": 1,
            "macc": 4160,
            "name": "dense_1_dense",
            "next": "dense_1",
            "op_by_type": {
                "smul_f32_f32": 4160
            },
            "rom": 16640,
            "tensors": {
                "inputs": [
                    "dense_output"
                ],
                "outputs": [
                    "dense_1_dense_output"
                ],
                "scratchs": [],
                "weights": [
                    "dense_1_dense_weights",
                    "dense_1_dense_bias"
                ]
            },
            "weight_sparsity": [
                0.0028846153846153744,
                4160,
                12
            ]
        },
        {
            "c_forward": "forward_relu",
            "c_id": 3,
            "exec_time": {
                "cycles": 0,
                "cycles_by_macc": 0.0,
                "duration_ms": 0.0005000000237487257,
                "percentage": 9.09090921117285
            },
            "layer_type": "nl",
            "m_id": 1,
            "macc": 64,
            "name": "dense_1",
            "next": "dense_2_dense",
            "op_by_type": {
                "op_f32_f32": 64
            },
            "rom": 0,
            "tensors": {
                "inputs": [
                    "dense_1_dense_output"
                ],
                "outputs": [
                    "dense_1_output"
                ],
                "scratchs": [],
                "weights": []
            },
            "weight_sparsity": [
                0.0,
                0,
                0
            ]
        },
        {
            "c_forward": "forward_dense",
            "c_id": 4,
            "exec_time": {
                "cycles": 0,
                "cycles_by_macc": 0.0,
                "duration_ms": 0.0005000000237487257,
                "percentage": 9.09090921117285
            },
            "layer_type": "dense",
            "m_id": 2,
            "macc": 65,
            "name": "dense_2_dense",
            "next": "dense_2_dense",
            "op_by_type": {
                "smul_f32_f32": 65
            },
            "rom": 260,
            "tensors": {
                "inputs": [
                    "dense_1_output"
                ],
                "outputs": [
                    "dense_2_dense_output"
                ],
                "scratchs": [],
                "weights": [
                    "dense_2_dense_weights",
                    "dense_2_dense_bias"
                ]
            },
            "weight_sparsity": [
                0.0,
                65,
                0
            ]
        }
    ],
    "c_name": "model_2",
    "c_nodes_n": 5,
    "c_tensors_n": 12,
    "c_weights_count": 1,
    "c_weights_header": 0,
    "data_alignment": 4,
    "date_time": "Tue Oct  4 13:52:28 2022",
    "exec_time": {
        "cycles": 0,
        "cycles_by_macc": 0.0,
        "device": "AMD64 Intel64 Family 6 Model 140 Stepping 1, GenuineIntel (Windows)",
        "duration_ms": 0.005500000188476406
    },
    "inputs": [
        "input_0_output"
    ],
    "macc": 5249,
    "memory_footprint": {
        "activations": 512,
        "io": [
            0,
            0
        ],
        "series": "generic",
        "weights": 20484
    },
    "memory_pools": [],
    "model_name": "housing",
    "outputs": [
        "dense_2_dense_output"
    ],
    "params_alignment": 4,
    "stm_ai_version": {
        "extra": "RC1",
        "major": 7,
        "micro": 0,
        "minor": 2
    },
    "tool_api_version": {
        "major": 1,
        "micro": 0,
        "minor": 5
    },
    "tool_version": {
        "major": 1,
        "micro": 0,
        "minor": 6
    },
    "version": "1.2",
    "weights": {
        "weights_array": {
            "buffer_c_name": "NULL",
            "buffer_c_name_addr": "NULL",
            "buffer_data_size": 20484,
            "buffer_offsets": [
                {
                    "buffer_name": "dense_dense_weights_array",
                    "lite_tag": null,
                    "offset": 0,
                    "size": 3328,
                    "start_offset": 0
                },
                {
                    "buffer_name": "dense_dense_bias_array",
                    "lite_tag": null,
                    "offset": 3328,
                    "size": 256,
                    "start_offset": 3328
                },
                {
                    "buffer_name": "dense_1_dense_weights_array",
                    "lite_tag": null,
                    "offset": 3584,
                    "size": 16384,
                    "start_offset": 3584
                },
                {
                    "buffer_name": "dense_1_dense_bias_array",
                    "lite_tag": null,
                    "offset": 19968,
                    "size": 256,
                    "start_offset": 19968
                },
                {
                    "buffer_name": "dense_2_dense_weights_array",
                    "lite_tag": null,
                    "offset": 20224,
                    "size": 256,
                    "start_offset": 20224
                },
                {
                    "buffer_name": "dense_2_dense_bias_array",
                    "lite_tag": null,
                    "offset": 20480,
                    "size": 4,
                    "start_offset": 20480
                }
            ],
            "pool_id": 0,
            "pool_size": 20484
        }
    }
}